pysweepme/Architecture.py
pysweepme/Config.py
pysweepme/DeviceManager.py
pysweepme/EmptyDeviceClass.py
pysweepme/ErrorMessage.py
pysweepme/FolderManager.py
pysweepme/PortManager.py
pysweepme/Ports.py
pysweepme/UserInterface.py
pysweepme/WinFolder.py
pysweepme/__init__.py
pysweepme/_utils.py
pysweepme/pysweepme_types.py
pysweepme-1.5.7.5.dist-info/licenses/LICENSE.md
pysweepme-1.5.7.5.dist-info/METADATA
pysweepme-1.5.7.5.dist-info/WHEEL
pysweepme-1.5.7.5.dist-info/top_level.txt
pysweepme-1.5.7.5.dist-info/RECORD
