Metadata-Version: 2.4
Name: pysweepme
Version: 1.5.7.5
Summary: Load SweepMe! instrument drivers in your own python projects.
Maintainer-email: SweepMe! GmbH <contact@sweep-me.net>
License-Expression: MIT
Project-URL: Homepage, https://sweep-me.net
Project-URL: Repository, https://github.com/SweepMe/pysweepme
Classifier: Programming Language :: Python :: 3
Classifier: Operating System :: Microsoft :: Windows
Classifier: Intended Audience :: Developers
Classifier: Intended Audience :: Science/Research
Classifier: Topic :: Scientific/Engineering
Classifier: Topic :: System :: Hardware :: Hardware Drivers
Requires-Python: <3.12,>=3.9
License-File: LICENSE.md
Requires-Dist: psutil~=5.9.3
Requires-Dist: pythonnet~=3.0.0.post1
Requires-Dist: pyserial~=3.5
Requires-Dist: PyVISA~=1.13.0
Provides-Extra: dev
Requires-Dist: tox~=4.6.1; extra == "dev"
Requires-Dist: ruff~=0.0.272; extra == "dev"
Requires-Dist: black~=23.3.0; extra == "dev"
Requires-Dist: mypy~=1.3.0; extra == "dev"
Requires-Dist: pytest~=7.3.2; extra == "dev"
Provides-Extra: typed
Requires-Dist: types-psutil~=5.9.3; extra == "typed"
Requires-Dist: types-pyserial~=3.5; extra == "typed"
Dynamic: license-file
